setup.py
django_picasa.egg-info/PKG-INFO
django_picasa.egg-info/SOURCES.txt
django_picasa.egg-info/dependency_links.txt
django_picasa.egg-info/not-zip-safe
django_picasa.egg-info/requires.txt
django_picasa.egg-info/top_level.txt
picasa/__init__.py
picasa/fields.py
picasa/storage.py
tests/examplesite/__init__.py
tests/examplesite/archive.db
tests/examplesite/manage.py
tests/examplesite/settings.py
tests/examplesite/urls.py
tests/examplesite/archive/__init__.py
tests/examplesite/archive/admin.py
tests/examplesite/archive/models.py
tests/examplesite/archive/tests.py
tests/examplesite/archive/views.py