Metadata-Version: 1.0
Name: django-picasa
Version: 1.3
Summary: A module of django components that give you picasa storage, picasa fileds and admin fields.
Home-page: http://code.google.com/p/django-googledata/
Author: Thanos Vassilakis
Author-email: thanos@syntazo.com
License: UNKNOWN
Keywords: picassa,storage,images,photos,django,google
Platform: UNKNOWN
Classifier: Development Status :: 5 - Production/Stable
Classifier: Environment :: Web Environment
Classifier: Framework :: Django
Classifier: Intended Audience :: Developers
Classifier: License :: OSI Approved :: Apache Software License
Classifier: Operating System :: OS Independent
Classifier: Programming Language :: Python
Classifier: Topic :: Internet :: WWW/HTTP :: Dynamic Content :: CGI Tools/Libraries
Classifier: Topic :: Software Development :: Libraries :: Python Modules
